.bumpversion.cfg
.cookiecutterrc
.coveragerc
.editorconfig
.travis.yml
AUTHORS.rst
CHANGELOG.rst
CONTRIBUTING.rst
LICENSE
MANIFEST.in
README.rst
appveyor.yml
setup.cfg
setup.py
tox.ini
ci/appveyor-bootstrap.py
ci/appveyor-download.py
ci/appveyor-with-compiler.cmd
ci/bootstrap.py
ci/templates/.travis.yml
ci/templates/appveyor.yml
docs/authors.rst
docs/changelog.rst
docs/conf.py
docs/contributing.rst
docs/index.rst
docs/installation.rst
docs/readme.rst
docs/requirements.txt
docs/spelling_wordlist.txt
docs/usage.rst
docs/reference/index.rst
docs/reference/mongosizeof.rst
src/mongosizeof/__init__.py
src/mongosizeof/_cython_impl.c
src/mongosizeof/_cython_impl.pyx
src/mongosizeof/_python_impl.py
src/mongosizeof.egg-info/PKG-INFO
src/mongosizeof.egg-info/SOURCES.txt
src/mongosizeof.egg-info/dependency_links.txt
src/mongosizeof.egg-info/not-zip-safe
src/mongosizeof.egg-info/requires.txt
src/mongosizeof.egg-info/top_level.txt
tests/test_mongosizeof.py